pyperf2/__init__.py
pyperf2-0.4.8.dist-info/LICENSE
pyperf2-0.4.8.dist-info/METADATA
pyperf2-0.4.8.dist-info/WHEEL
pyperf2-0.4.8.dist-info/top_level.txt
pyperf2-0.4.8.dist-info/RECORD
