Metadata-Version: 2.1
Name: pyperf2
Version: 0.4.8
Summary: Abstraction layer for iperf2 linux binary
Home-page: https://github.com/jinjamator/pyperf2
Author: Wilhelm Putz
Author-email: wp@aci.guru
License: ASL V2
Platform: UNKNOWN
Classifier: License :: OSI Approved :: Apache Software License
Classifier: Programming Language :: Python :: 3.7
Classifier: Programming Language :: Python :: 3.8
Classifier: Topic :: System :: Installation/Setup
Classifier: Topic :: System :: Systems Administration
Classifier: Topic :: Utilities
Requires-Python: >=3.7
License-File: LICENSE
Requires-Dist: pyjq
Requires-Dist: pyroute2
